{
  "plants": [
    { "name": "Arabidopsis",  "unlockAt": 0,  "bonusStat": "",           "bonusAmount": 0.0  },
    { "name": "Nicotiana",    "unlockAt": 6,  "bonusStat": "",           "bonusAmount": 0.0  },
    { "name": "Daucus",       "unlockAt": 12, "bonusStat": "",           "bonusAmount": 0.0  },
    { "name": "Spinacia",     "unlockAt": 18, "bonusStat": "",           "bonusAmount": 0.0  },
    { "name": "Cucumis",      "unlockAt": 24, "bonusStat": "Speed",      "bonusAmount": 0.15 },
    { "name": "Phaseolus",    "unlockAt": 30, "bonusStat": "",           "bonusAmount": 0.0  },
    { "name": "Medicago",     "unlockAt": 36, "bonusStat": "Resistance", "bonusAmount": 0.2  },
    { "name": "Capsicum",     "unlockAt": 42, "bonusStat": "",           "bonusAmount": 0.0  },
    { "name": "Lycopersicon", "unlockAt": 48, "bonusStat": "Effective",  "bonusAmount": 0.2  },
    { "name": "Brassica",     "unlockAt": 54, "bonusStat": "",           "bonusAmount": 0.0  },
    { "name": "Oryza",        "unlockAt": 60, "bonusStat": "Speed",      "bonusAmount": 0.25 },
    { "name": "Solanum",      "unlockAt": 66, "bonusStat": "",           "bonusAmount": 0.0  },
    { "name": "Glycine",      "unlockAt": 72, "bonusStat": "Resistance", "bonusAmount": 0.25 },
    { "name": "Triticum",     "unlockAt": 78, "bonusStat": "Effective",  "bonusAmount": 0.3  },
    { "name": "Zea",          "unlockAt": 84, "bonusStat": "Speed",      "bonusAmount": 0.3  },
    { "name": "Helianthus",   "unlockAt": 90, "bonusStat": "Resistance", "bonusAmount": 0.35 }
  ]
}
